odoo/addons/stock_putaway_hook/README.rst
odoo/addons/stock_putaway_hook/__init__.py
odoo/addons/stock_putaway_hook/__manifest__.py
odoo/addons/stock_putaway_hook/i18n/it.po
odoo/addons/stock_putaway_hook/i18n/stock_putaway_hook.pot
odoo/addons/stock_putaway_hook/models/__init__.py
odoo/addons/stock_putaway_hook/models/stock_location.py
odoo/addons/stock_putaway_hook/models/stock_putaway_rule.py
odoo/addons/stock_putaway_hook/readme/CONTRIBUTORS.rst
odoo/addons/stock_putaway_hook/readme/DESCRIPTION.rst
odoo/addons/stock_putaway_hook/readme/USAGE.rst
odoo/addons/stock_putaway_hook/static/description/icon.png
odoo/addons/stock_putaway_hook/static/description/index.html
odoo14_addon_stock_putaway_hook-14.0.1.0.1.dev6.dist-info/METADATA
odoo14_addon_stock_putaway_hook-14.0.1.0.1.dev6.dist-info/WHEEL
odoo14_addon_stock_putaway_hook-14.0.1.0.1.dev6.dist-info/top_level.txt
odoo14_addon_stock_putaway_hook-14.0.1.0.1.dev6.dist-info/RECORD
